itpwriter/cli.py
itpwriter/templates/itp.jinja
itpwriter-0.1.0.dist-info/LICENSE
itpwriter-0.1.0.dist-info/METADATA
itpwriter-0.1.0.dist-info/WHEEL
itpwriter-0.1.0.dist-info/entry_points.txt
itpwriter-0.1.0.dist-info/RECORD
